libname/__init__.py
libname/slotgacor.py
slot_gacor-0.0.2.dist-info/METADATA
slot_gacor-0.0.2.dist-info/WHEEL
slot_gacor-0.0.2.dist-info/top_level.txt
slot_gacor-0.0.2.dist-info/RECORD
