Metadata-Version: 2.1
Name: slot-gacor
Version: 0.0.2
Summary: Daftar Link Bocoran Slot Gacor
Home-page: UNKNOWN
Author: QQBARENG
Author-email: <qqbareng@preout.download>
License: UNKNOWN
Keywords: slot,slot gacor,slot gacor hari ini,link slot gacor,slot online
Platform: UNKNOWN
Classifier: Development Status :: 1 - Planning
Classifier: Intended Audience :: Developers
Classifier: Programming Language :: Python :: 3
Classifier: Operating System :: Unix
Classifier: Operating System :: MacOS :: MacOS X
Classifier: Operating System :: Microsoft :: Windows
